pyactionnetwork/__init__.py
pyactionnetwork/api.py
pyactionnetwork/helpers.py
pyactionnetwork/models.py
pyActionNetwork-0.11.2.dist-info/LICENSE
pyActionNetwork-0.11.2.dist-info/METADATA
pyActionNetwork-0.11.2.dist-info/WHEEL
pyActionNetwork-0.11.2.dist-info/top_level.txt
pyActionNetwork-0.11.2.dist-info/RECORD
