Metadata-Version: 2.1
Name: pyActionNetwork
Version: 0.11.2
Summary: Python API client for ActionNetwork
Home-page: https://github.com/phillydsa/pyActionNetwork
Author: Jeremy Low
Author-email: jeremy@iseverythingstilltheworst.com
License: MIT
Keywords: api actionnetwork client
Platform: UNKNOWN
Classifier: Development Status :: 3 - Alpha
Classifier: Intended Audience :: Developers
Classifier: License :: OSI Approved :: MIT License
Classifier: Programming Language :: Python :: 3
Classifier: Programming Language :: Python :: 3.3
Classifier: Programming Language :: Python :: 3.4
Classifier: Programming Language :: Python :: 3.5
Classifier: Programming Language :: Python :: 3.6
Requires-Dist: requests
Requires-Dist: python-dateutil
Provides-Extra: dev
Requires-Dist: check-manifest ; extra == 'dev'
Provides-Extra: test
Requires-Dist: coverage ; extra == 'test'
